img2segy/__init__.py
img2segy/__main__.py
img2segy/api.py
img2segy/cli.py
img2segy/geometry.py
img2segy/image_dataset.py
img2segy/trace_header_mapper.py
img2segy/version.py
img2segy-1.1.3.dist-info/LICENSE.txt
img2segy-1.1.3.dist-info/METADATA
img2segy-1.1.3.dist-info/WHEEL
img2segy-1.1.3.dist-info/entry_points.txt
img2segy-1.1.3.dist-info/top_level.txt
img2segy-1.1.3.dist-info/zip-safe
img2segy-1.1.3.dist-info/RECORD
