Metadata-Version: 2.1
Name: img2segy
Version: 1.1.3
Summary: A tool for converting images to SEG-Y
Home-page: https://github.com/sixty-north/img2segy
Author: Sixty North AS
Author-email: systems+img2segy@sixty-north.com
License: GNU Affero General Public License v3
Keywords: seismic image-processing geocomputing geophysics
Classifier: Development Status :: 5 - Production/Stable
Classifier: Environment :: Console
Classifier: Intended Audience :: Information Technology
Classifier: Topic :: Scientific/Engineering
Classifier: License :: OSI Approved :: GNU Affero General Public License v3
Classifier: Programming Language :: Python :: 3 :: Only
Classifier: Programming Language :: Python :: 3.7
Classifier: Programming Language :: Python :: 3.8
Classifier: Programming Language :: Python :: 3.9
Classifier: Programming Language :: Python :: 3.10
License-File: LICENSE.txt
Requires-Dist: click (>=8.1.3)
Requires-Dist: euclidian (>=0.9.2)
Requires-Dist: exit-codes (>=1.3.0)
Requires-Dist: numpy (>=1.23.2)
Requires-Dist: segpy (>=2.1.0)
Requires-Dist: toml (>=0.10.2)
Provides-Extra: dev
Requires-Dist: black ; extra == 'dev'
Requires-Dist: bumpversion ; extra == 'dev'
Requires-Dist: twine ; extra == 'dev'
Requires-Dist: build ; extra == 'dev'
Provides-Extra: doc
Requires-Dist: sphinx ; extra == 'doc'
Requires-Dist: sphinx-rtd-theme ; extra == 'doc'
Requires-Dist: better-apidoc ; extra == 'doc'
Provides-Extra: test
Requires-Dist: pytest ; extra == 'test'
Requires-Dist: hypothesis ; extra == 'test'
Requires-Dist: tox ; extra == 'test'
